odoo/addons/hr_employee_phone_extension/README.rst
odoo/addons/hr_employee_phone_extension/__init__.py
odoo/addons/hr_employee_phone_extension/__manifest__.py
odoo/addons/hr_employee_phone_extension/i18n/ar.po
odoo/addons/hr_employee_phone_extension/i18n/cs_CZ.po
odoo/addons/hr_employee_phone_extension/i18n/de.po
odoo/addons/hr_employee_phone_extension/i18n/es.po
odoo/addons/hr_employee_phone_extension/i18n/fi.po
odoo/addons/hr_employee_phone_extension/i18n/fr.po
odoo/addons/hr_employee_phone_extension/i18n/hr.po
odoo/addons/hr_employee_phone_extension/i18n/hr_HR.po
odoo/addons/hr_employee_phone_extension/i18n/hr_employee_phone_extension.pot
odoo/addons/hr_employee_phone_extension/i18n/it.po
odoo/addons/hr_employee_phone_extension/i18n/lt.po
odoo/addons/hr_employee_phone_extension/i18n/nl_NL.po
odoo/addons/hr_employee_phone_extension/i18n/pt_BR.po
odoo/addons/hr_employee_phone_extension/i18n/ro.po
odoo/addons/hr_employee_phone_extension/i18n/sl.po
odoo/addons/hr_employee_phone_extension/models/__init__.py
odoo/addons/hr_employee_phone_extension/models/hr_employee.py
odoo/addons/hr_employee_phone_extension/readme/CONTRIBUTORS.rst
odoo/addons/hr_employee_phone_extension/readme/DESCRIPTION.rst
odoo/addons/hr_employee_phone_extension/readme/INSTALL.rst
odoo/addons/hr_employee_phone_extension/readme/USAGE.rst
odoo/addons/hr_employee_phone_extension/static/description/icon.png
odoo/addons/hr_employee_phone_extension/static/description/index.html
odoo/addons/hr_employee_phone_extension/views/hr_employee_view.xml
odoo12_addon_hr_employee_phone_extension-12.0.1.0.0.99.dev8.dist-info/METADATA
odoo12_addon_hr_employee_phone_extension-12.0.1.0.0.99.dev8.dist-info/WHEEL
odoo12_addon_hr_employee_phone_extension-12.0.1.0.0.99.dev8.dist-info/top_level.txt
odoo12_addon_hr_employee_phone_extension-12.0.1.0.0.99.dev8.dist-info/RECORD
